gitignore_cli_tddschn/__init__.py
gitignore_cli_tddschn/cli.py
gitignore_cli_tddschn-0.4.1.dist-info/entry_points.txt
gitignore_cli_tddschn-0.4.1.dist-info/WHEEL
gitignore_cli_tddschn-0.4.1.dist-info/METADATA
gitignore_cli_tddschn-0.4.1.dist-info/RECORD
