Metadata-Version: 2.1
Name: gitignore-cli-tddschn
Version: 0.4.1
Summary: Fast gitignore CLI tool with cached templates
Home-page: https://github.com/tddschn/gitignore-cli-tddschn
License: MIT
Keywords: gitignore,cli,git
Author: Xinyuan Chen
Author-email: 45612704+tddschn@users.noreply.github.com
Requires-Python: >=3.10,<4.0
Classifier: License :: OSI Approved :: MIT License
Classifier: Programming Language :: Python :: 3
Classifier: Programming Language :: Python :: 3.10
Classifier: Topic :: Utilities
Requires-Dist: utils-tddschn (>=1.0.0)
Project-URL: Bug Tracker, https://github.com/tddschn/gitignore-cli-tddschn/issues
Project-URL: Repository, https://github.com/tddschn/gitignore-cli-tddschn
